{
  "version": 1,
  "rootId": "augment-enhance",
  "root": "augment=enhance",
  "meaning": "augment=enhance",
  "descriptionCn": "增加",
  "updatedAt": "2026-04-18",
  "words": [
    {
      "id": "augment-augment-enhance-2",
      "word": "augment",
      "display": "Augment",
      "phonetic": "/ɔgˈmɛnt/",
      "translation": "增加",
      "sentence": "The recent speech of the president augmented tensions in the Near East",
      "tags": [
        "root-family",
        "other"
      ],
      "level": 1
    },
    {
      "id": "enhance-augment-enhance-2",
      "word": "enhance",
      "display": "Enhance",
      "phonetic": "/ɛnˈhæns/",
      "translation": "增加",
      "sentence": "This will enhance your enjoyment",
      "tags": [
        "root-family",
        "other"
      ],
      "level": 1
    }
  ],
  "parentRootId": "ad-a-an",
  "rootLevel": 5,
  "rootPath": "a>a-prefix>ad-add-axx>ad-a-an>augment-enhance",
  "type": "branch",
  "notes": "根据 词根.txt 整理",
  "tags": []
}
