{
  "version": 1,
  "rootId": "c-wrap-clo",
  "root": "clo",
  "meaning": "clo family",
  "descriptionCn": "clo 词族",
  "updatedAt": "2026-04-18",
  "words": [
    {
      "id": "c-wrap-clo-clause",
      "word": "clause",
      "display": "Clause",
      "phonetic": "/klɔz/",
      "translation": "条款；从句",
      "sentence": "A clause is (grammar) an expression including a subject and predicate but not constituting a complete sentence.",
      "tags": [
        "root-family"
      ],
      "level": 1
    },
    {
      "id": "c-wrap-clo-claustra",
      "word": "claustra",
      "display": "Claustra",
      "phonetic": "/klˈɔstrʌ/",
      "translation": "修道院的",
      "sentence": "Claustra is used here with the sense of \"修道院的\".",
      "tags": [
        "root-family"
      ],
      "level": 1
    },
    {
      "id": "c-wrap-clo-claustrophobia",
      "word": "claustrophobia",
      "display": "Claustrophobia",
      "phonetic": "/ˌklɔstrəˈfoʊbiə/",
      "translation": "幽闭恐惧症",
      "sentence": "A claustrophobia is a morbid fear of being closed in a confined space.",
      "tags": [
        "root-family"
      ],
      "level": 1
    },
    {
      "id": "c-wrap-clo-cloister",
      "word": "cloister",
      "display": "Cloister",
      "phonetic": "/ˈklɔɪstər/",
      "translation": "修道院；回廊",
      "sentence": "cloister the garden",
      "tags": [
        "root-family"
      ],
      "level": 1
    },
    {
      "id": "c-wrap-clo-cloistral",
      "word": "cloistral",
      "display": "Cloistral",
      "phonetic": "/klˈaɪstrʌl/",
      "translation": "修道院的",
      "sentence": "If something is cloistral, it is of communal life sequestered from the world under religious vows.",
      "tags": [
        "root-family"
      ],
      "level": 1
    },
    {
      "id": "c-wrap-clo-close",
      "word": "close",
      "display": "Close",
      "phonetic": "/kloʊz/",
      "translation": "关闭；紧密的；亲密的",
      "sentence": "they were playing better at the close of the season",
      "tags": [
        "root-family"
      ],
      "level": 1
    },
    {
      "id": "c-wrap-clo-closet",
      "word": "closet",
      "display": "Closet",
      "phonetic": "/ˈklɑzət/",
      "translation": "橱柜",
      "sentence": "A closet is a small room (or recess) or cabinet used for storage space.",
      "tags": [
        "root-family"
      ],
      "level": 1
    },
    {
      "id": "c-wrap-clo-closure",
      "word": "closure",
      "display": "Closure",
      "phonetic": "/ˈkloʊʒər/",
      "translation": "关闭",
      "sentence": "he needed to grieve before he could achieve a sense of closure",
      "tags": [
        "root-family"
      ],
      "level": 1
    },
    {
      "id": "c-wrap-clo-conclude",
      "word": "conclude",
      "display": "Conclude",
      "phonetic": "/kənˈklud/",
      "translation": "决定；做结论",
      "sentence": "The committee concluded the meeting",
      "tags": [
        "root-family"
      ],
      "level": 1
    },
    {
      "id": "c-wrap-clo-conclusion",
      "word": "conclusion",
      "display": "Conclusion",
      "phonetic": "/kənˈkluʒən/",
      "translation": "结论；结局",
      "sentence": "his conclusion took the evidence into account",
      "tags": [
        "root-family"
      ],
      "level": 1
    },
    {
      "id": "c-wrap-clo-conclusive",
      "word": "conclusive",
      "display": "Conclusive",
      "phonetic": "/kənˈklusɪv/",
      "translation": "决定性的",
      "sentence": "conclusive proof",
      "tags": [
        "root-family"
      ],
      "level": 1
    },
    {
      "id": "c-wrap-clo-disclose",
      "word": "disclose",
      "display": "Disclose",
      "phonetic": "/dɪˈskloʊz/",
      "translation": "公开",
      "sentence": "The auction house would not disclose the price at which the van Gogh had sold",
      "tags": [
        "root-family"
      ],
      "level": 1
    },
    {
      "id": "c-wrap-clo-disclosure",
      "word": "disclosure",
      "display": "Disclosure",
      "phonetic": "/dɪˈskloʊʒər/",
      "translation": "揭发",
      "sentence": "A disclosure is the speech act of making something evident.",
      "tags": [
        "root-family"
      ],
      "level": 1
    },
    {
      "id": "c-wrap-clo-enclose",
      "word": "enclose",
      "display": "Enclose",
      "phonetic": "/ɪnˈkloʊz/",
      "translation": "围绕；放入袋中",
      "sentence": "Darkness enclosed him",
      "tags": [
        "root-family"
      ],
      "level": 1
    },
    {
      "id": "c-wrap-clo-enclosure",
      "word": "enclosure",
      "display": "Enclosure",
      "phonetic": "/ɪnˈkloʊʒər/",
      "translation": "附件；包含物；围墙",
      "sentence": "An enclosure is a structure consisting of an area that has been enclosed for some purpose.",
      "tags": [
        "root-family"
      ],
      "level": 1
    },
    {
      "id": "c-wrap-clo-exclude",
      "word": "exclude",
      "display": "Exclude",
      "phonetic": "/ɪkˈsklud/",
      "translation": "排除",
      "sentence": "The bad results were excluded from the report",
      "tags": [
        "root-family"
      ],
      "level": 1
    },
    {
      "id": "c-wrap-clo-exclusion",
      "word": "exclusion",
      "display": "Exclusion",
      "phonetic": "/ɪkˈskluʒən/",
      "translation": "排除",
      "sentence": "with the exception of the children, everyone was told the news",
      "tags": [
        "root-family"
      ],
      "level": 1
    },
    {
      "id": "c-wrap-clo-include",
      "word": "include",
      "display": "Include",
      "phonetic": "/ˌɪnˈklud/",
      "translation": "包括",
      "sentence": "The list includes the names of many famous writers",
      "tags": [
        "root-family"
      ],
      "level": 1
    },
    {
      "id": "c-wrap-clo-inclusion",
      "word": "inclusion",
      "display": "Inclusion",
      "phonetic": "/ˌɪnˈkluʒən/",
      "translation": "包含",
      "sentence": "he admired the inclusion of so many ideas in such a short work",
      "tags": [
        "root-family"
      ],
      "level": 1
    },
    {
      "id": "c-wrap-clo-inclusive",
      "word": "inclusive",
      "display": "Inclusive",
      "phonetic": "/ˌɪnˈklusɪv/",
      "translation": "包含的",
      "sentence": "an inclusive art form",
      "tags": [
        "root-family"
      ],
      "level": 1
    }
  ],
  "type": "root",
  "rootPath": "c>c-wrap>c-wrap-clo",
  "rootLevel": 3,
  "parentRootId": "c-wrap",
  "tags": []
}
