{
  "version": 1,
  "rootId": "f-other-fabl",
  "root": "fabl=fabul说话",
  "meaning": "fabl",
  "descriptionCn": "说话",
  "updatedAt": "2026-04-18",
  "words": [
    {
      "id": "f-other-fabl-affability",
      "word": "affability",
      "display": "Affability",
      "phonetic": "/ˌæfʌbˈɪlʌti/",
      "translation": "和蔼",
      "sentence": "An affability is a disposition to be friendly and approachable (easy to talk to).",
      "tags": [
        "root-family"
      ],
      "level": 1
    },
    {
      "id": "f-other-fabl-affable",
      "word": "affable",
      "display": "Affable",
      "phonetic": "/ˈæfəbəl/",
      "translation": "亲切的",
      "sentence": "an affable smile",
      "tags": [
        "root-family"
      ],
      "level": 1
    },
    {
      "id": "f-other-fabl-confabulate",
      "word": "confabulate",
      "display": "Confabulate",
      "phonetic": "/kʌnfˈɑbʌlˌeɪt/",
      "translation": "交谈",
      "sentence": "the men were sitting in the cafe and shooting the breeze",
      "tags": [
        "root-family"
      ],
      "level": 1
    },
    {
      "id": "f-other-fabl-effable",
      "word": "effable",
      "display": "Effable",
      "phonetic": "/ˈɛfʌbʌl/",
      "translation": "可表达的",
      "sentence": "Effable is used here with the sense of \"可表达的\".",
      "tags": [
        "root-family"
      ],
      "level": 1
    },
    {
      "id": "f-other-fabl-fable",
      "word": "fable",
      "display": "Fable",
      "phonetic": "/ˈfeɪbəl/",
      "translation": "童话",
      "sentence": "A fable is a deliberately false or improbable account.",
      "tags": [
        "root-family"
      ],
      "level": 1
    },
    {
      "id": "f-other-fabl-fabulate",
      "word": "fabulate",
      "display": "Fabulate",
      "phonetic": "/fˈæbjulˌeɪt/",
      "translation": "寓言创作",
      "sentence": "Fabulate is used here with the sense of \"寓言创作\".",
      "tags": [
        "root-family"
      ],
      "level": 1
    },
    {
      "id": "f-other-fabl-fabulist",
      "word": "fabulist",
      "display": "Fabulist",
      "phonetic": "/fˈæbjulɪst/",
      "translation": "寓言家",
      "sentence": "A fabulist is a person who tells or invents fables.",
      "tags": [
        "root-family"
      ],
      "level": 1
    },
    {
      "id": "f-other-fabl-fabulosity",
      "word": "fabulosity",
      "display": "Fabulosity",
      "phonetic": "/fˌæbjulˈæsʌti/",
      "translation": "寓言性质",
      "sentence": "Fabulosity is used here with the sense of \"寓言性质\".",
      "tags": [
        "root-family"
      ],
      "level": 1
    }
  ],
  "parentRootId": "f-other",
  "rootLevel": 3,
  "rootPath": "f>f-other>f-other-fabl",
  "type": "branch",
  "notes": "",
  "tags": []
}
