{
  "version": 1,
  "rootId": "r-re-emotion",
  "root": "情感",
  "meaning": "emotion",
  "descriptionCn": "情感",
  "updatedAt": "2026-04-18",
  "words": [
    {
      "id": "r-re-emotion-refresh",
      "word": "refresh",
      "display": "Refresh",
      "phonetic": "/rɪˈfrɛʃ/",
      "translation": "使精神振作",
      "sentence": "The cool water refreshed us",
      "tags": [
        "root-family"
      ],
      "level": 1
    },
    {
      "id": "r-re-emotion-refreshment",
      "word": "refreshment",
      "display": "Refreshment",
      "phonetic": "/rəˈfrɛʃmənt/",
      "translation": "点心；饮料",
      "sentence": "time for rest and refreshment by the pool",
      "tags": [
        "root-family"
      ],
      "level": 1
    },
    {
      "id": "r-re-emotion-rejoice",
      "word": "rejoice",
      "display": "Rejoice",
      "phonetic": "/rɪˈʤɔɪs/",
      "translation": "使高兴",
      "sentence": "Who cannot exult in Spring?",
      "tags": [
        "root-family"
      ],
      "level": 1
    },
    {
      "id": "r-re-emotion-relax",
      "word": "relax",
      "display": "Relax",
      "phonetic": "/rɪˈlæks/",
      "translation": "放松",
      "sentence": "He relaxed in the hot tub",
      "tags": [
        "root-family"
      ],
      "level": 1
    },
    {
      "id": "r-re-emotion-relay",
      "word": "relay",
      "display": "Relay",
      "phonetic": "/ˈriˌleɪ/",
      "translation": "接力；接班",
      "sentence": "the relay was successful",
      "tags": [
        "root-family"
      ],
      "level": 1
    },
    {
      "id": "r-re-emotion-release",
      "word": "release",
      "display": "Release",
      "phonetic": "/riˈlis/",
      "translation": "释放",
      "sentence": "a new release from the London Symphony Orchestra",
      "tags": [
        "root-family"
      ],
      "level": 1
    },
    {
      "id": "r-re-emotion-relief",
      "word": "relief",
      "display": "Relief",
      "phonetic": "/rɪˈlif/",
      "translation": "减轻；解除",
      "sentence": "as he heard the news he was suddenly flooded with relief",
      "tags": [
        "root-family"
      ],
      "level": 1
    },
    {
      "id": "r-re-emotion-relieve",
      "word": "relieve",
      "display": "Relieve",
      "phonetic": "/rɪˈliv/",
      "translation": "减轻",
      "sentence": "This pill will relieve your headaches",
      "tags": [
        "root-family"
      ],
      "level": 1
    },
    {
      "id": "r-re-emotion-reluctant",
      "word": "reluctant",
      "display": "Reluctant",
      "phonetic": "/rɪˈləktənt/",
      "translation": "不愿的；勉强的",
      "sentence": "a reluctant smile",
      "tags": [
        "root-family"
      ],
      "level": 1
    },
    {
      "id": "r-re-emotion-resolute",
      "word": "resolute",
      "display": "Resolute",
      "phonetic": "/ˈrɛzəˌlut/",
      "translation": "坚决的",
      "sentence": "stood resolute against the enemy",
      "tags": [
        "root-family"
      ],
      "level": 1
    },
    {
      "id": "r-re-emotion-resolution",
      "word": "resolution",
      "display": "Resolution",
      "phonetic": "/ˌrɛzəˈluʃən/",
      "translation": "坚决",
      "sentence": "it was his unshakeable resolution to finish the work",
      "tags": [
        "root-family"
      ],
      "level": 1
    }
  ],
  "parentRootId": "r-re",
  "rootLevel": 3,
  "rootPath": "r>r-re>r-re-emotion",
  "type": "root",
  "notes": "",
  "tags": []
}
