{
  "version": 1,
  "rootId": "s-she",
  "root": "她--害羞--阴影--发光--避难所",
  "meaning": "she, shy, shadow, shine, shelter",
  "descriptionCn": "她--害羞--阴影--发光--避难所",
  "updatedAt": "2026-04-18",
  "words": [
    {
      "id": "s-she-shabby",
      "word": "shabby",
      "display": "Shabby",
      "phonetic": "/ˈʃæbi/",
      "translation": "简陋的",
      "sentence": "shabby furniture",
      "tags": [
        "root-family"
      ],
      "level": 1
    },
    {
      "id": "s-she-shaby",
      "word": "shaby",
      "display": "Shaby",
      "phonetic": "/ʃˈeɪbi/",
      "translation": "成荫的",
      "sentence": "Shaby is used here with the sense of \"成荫的\".",
      "tags": [
        "root-family"
      ],
      "level": 1
    },
    {
      "id": "s-she-shade",
      "word": "shade",
      "display": "Shade",
      "phonetic": "/ʃeɪd/",
      "translation": "阴影",
      "sentence": "it is much cooler in the shade",
      "tags": [
        "root-family"
      ],
      "level": 1
    },
    {
      "id": "s-she-shadow",
      "word": "shadow",
      "display": "Shadow",
      "phonetic": "/ˈʃæˌdoʊ/",
      "translation": "阴影",
      "sentence": "a shadow over his happiness",
      "tags": [
        "root-family"
      ],
      "level": 1
    },
    {
      "id": "s-she-shaft",
      "word": "shaft",
      "display": "Shaft",
      "phonetic": "/ʃæft/",
      "translation": "轴；杆状物",
      "sentence": "she threw shafts of sarcasm",
      "tags": [
        "root-family"
      ],
      "level": 1
    },
    {
      "id": "s-she-shake",
      "word": "shake",
      "display": "Shake",
      "phonetic": "/ʃeɪk/",
      "translation": "颤抖",
      "sentence": "my faith has been shaken",
      "tags": [
        "root-family"
      ],
      "level": 1
    },
    {
      "id": "s-she-sham",
      "word": "sham",
      "display": "Sham",
      "phonetic": "/ʃæm/",
      "translation": "假冒的",
      "sentence": "He shammed a headache",
      "tags": [
        "root-family"
      ],
      "level": 1
    },
    {
      "id": "s-she-shame",
      "word": "shame",
      "display": "Shame",
      "phonetic": "/ʃeɪm/",
      "translation": "羞耻",
      "sentence": "one mistake brought shame to all his family",
      "tags": [
        "root-family"
      ],
      "level": 1
    },
    {
      "id": "s-she-shed",
      "word": "shed",
      "display": "Shed",
      "phonetic": "/ʃɛd/",
      "translation": "小屋；脱落",
      "sentence": "he shed his image as a pushy boss",
      "tags": [
        "root-family"
      ],
      "level": 1
    },
    {
      "id": "s-she-sheer",
      "word": "sheer",
      "display": "Sheer",
      "phonetic": "/ʃɪr/",
      "translation": "陡峭的",
      "sentence": "She sheered her car around the obstacle",
      "tags": [
        "root-family"
      ],
      "level": 1
    },
    {
      "id": "s-she-shelter",
      "word": "shelter",
      "display": "Shelter",
      "phonetic": "/ˈʃɛltər/",
      "translation": "掩蔽",
      "sentence": "After the earthquake, the government could not provide shelter for the thousands of homeless people",
      "tags": [
        "root-family"
      ],
      "level": 1
    },
    {
      "id": "s-she-shiver",
      "word": "shiver",
      "display": "Shiver",
      "phonetic": "/ˈʃɪvər/",
      "translation": "颤抖",
      "sentence": "The children are shivering--turn on the heat!",
      "tags": [
        "root-family"
      ],
      "level": 1
    },
    {
      "id": "s-she-shock",
      "word": "shock",
      "display": "Shock",
      "phonetic": "/ʃɑk/",
      "translation": "震动；震惊",
      "sentence": "he was numb with shock",
      "tags": [
        "root-family"
      ],
      "level": 1
    }
  ],
  "parentRootId": "s",
  "rootLevel": 2,
  "rootPath": "s>s-she",
  "type": "root",
  "notes": "",
  "tags": []
}
